{
  "type": "cosmos-sdk/StdTx",
  "value": {
    "msg": [
      {
        "type": "cosmos-sdk/MsgCreateValidator",
        "value": {
          "description": {
            "moniker": "satoshi1",
            "identity": "",
            "website": "",
            "security_contact": "",
            "details": ""
          },
          "commission": {
            "rate": "0.100000000000000000",
            "max_rate": "0.200000000000000000",
            "max_change_rate": "0.010000000000000000"
          },
          "min_self_delegation": "1",
          "delegator_address": "tru1afactnpzk98s2uuxzqae6mr7zgudels4s4ad65",
          "validator_address": "truvaloper1afactnpzk98s2uuxzqae6mr7zgudels43yvwq8",
          "pubkey": "truvalconspub1zcjduepqg56g77upj8gdw9ljjzfja9w6f0rm4qwz9gf2n9hax9s0nn58a37ssu76eq",
          "value": {
            "denom": "utru",
            "amount": "10000000000"
          }
        }
      }
    ],
    "fee": {
      "amount": [],
      "gas": "200000"
    },
    "signatures": [
      {
        "pub_key": {
          "type": "tendermint/PubKeySecp256k1",
          "value": "Ay5zRZp/TcUrAilqlDhQriGiJAn6LOmSYYzAa7bWrRH7"
        },
        "signature": "Z46xPTP4tKpEMOGzdDM9QTyIe9eXYMEPL8K2GIhDZI1z4osVoq8cBa8PYvuuiiLzaCu2WZ8k4ePTIkOpAWNDZA=="
      }
    ],
    "memo": "53252d887ccea1aff0e5c8531228182a1b3a16fd@173.72.37.243:26656"
  }
}
